Katana-0.1.2.dist-info/DESCRIPTION.rst
Katana-0.1.2.dist-info/METADATA
Katana-0.1.2.dist-info/RECORD
Katana-0.1.2.dist-info/WHEEL
Katana-0.1.2.dist-info/entry_points.txt
Katana-0.1.2.dist-info/metadata.json
Katana-0.1.2.dist-info/top_level.txt
katana/__init__.py
katana/__main__.py
katana/cigar.py
katana/clipper.py
katana/pysamadapter.py
katana/readhandler.py
katana/util.py
