Metadata-Version: 2.0
Name: Katana
Version: 0.1.2
Summary: Command-line tool to soft-clip reads based on primer locations.
Home-page: https://github.com/umich-brcf-bioinf/Katana
Author: University of Michigan Bioinformatics Core
Author-email: bfx-katana@umich.edu
License: Apache
Keywords: bioinformatic exome-seq DNA-seq BAM
Platform: UNKNOWN
Classifier: Development Status :: 4 - Beta
Classifier: Environment :: Console
Classifier: Intended Audience :: Science/Research
Classifier: License :: OSI Approved :: Apache Software License
Classifier: Operating System :: Unix
Classifier: Programming Language :: Python :: 2.7
Classifier: Programming Language :: Python :: 3
Classifier: Topic :: Scientific/Engineering :: Bio-Informatics
Requires-Dist: natsort
Requires-Dist: pysam
